odoo/addons/connector_voicent/README.rst
odoo/addons/connector_voicent/__init__.py
odoo/addons/connector_voicent/__manifest__.py
odoo/addons/connector_voicent/data/ir_cron.xml
odoo/addons/connector_voicent/i18n/connector_voicent.pot
odoo/addons/connector_voicent/models/__init__.py
odoo/addons/connector_voicent/models/backend_voicent.py
odoo/addons/connector_voicent/models/backend_voicent_call_line.py
odoo/addons/connector_voicent/models/backend_voicent_time_line.py
odoo/addons/connector_voicent/models/res_partner.py
odoo/addons/connector_voicent/readme/CONFIGURATION.rst
odoo/addons/connector_voicent/readme/CONTRIBUTORS.rst
odoo/addons/connector_voicent/readme/DESCRIPTION.rst
odoo/addons/connector_voicent/readme/INSTALL.rst
odoo/addons/connector_voicent/readme/ROADMAP.rst
odoo/addons/connector_voicent/readme/USAGE.rst
odoo/addons/connector_voicent/security/ir.model.access.csv
odoo/addons/connector_voicent/static/description/icon.png
odoo/addons/connector_voicent/static/description/index.html
odoo/addons/connector_voicent/tests/__init__.py
odoo/addons/connector_voicent/tests/test_backend_voicent.py
odoo/addons/connector_voicent/views/backend_voicent.xml
odoo/addons/connector_voicent/views/backend_voicent_call_line.xml
odoo/addons/connector_voicent/views/res_partner.xml
odoo12_addon_connector_voicent-12.0.1.1.0.99.dev3.dist-info/METADATA
odoo12_addon_connector_voicent-12.0.1.1.0.99.dev3.dist-info/WHEEL
odoo12_addon_connector_voicent-12.0.1.1.0.99.dev3.dist-info/top_level.txt
odoo12_addon_connector_voicent-12.0.1.1.0.99.dev3.dist-info/RECORD
